streamanalyser/__init__.py
streamanalyser/streamanalyser.py
streamanalyser/data/default_contexts.json
streamanalyser/data/keyword_filters.txt
streamanalyser/data/monogram_stop_punctuations.txt
streamanalyser/data/monogram_stop_words.txt
streamanalyser/examples/__init__.py
streamanalyser/examples/custom_context.py
streamanalyser/examples/custom_intensity.py
streamanalyser/examples/custom_storage_path.py
streamanalyser/examples/find_users_with_more_than_one_comments.py
streamanalyser/examples/get_n_most_frequent_words.py
streamanalyser/examples/get_specific_messages_by_user.py
streamanalyser/examples/open_top_highlight_in_browser.py
streamanalyser/examples/show_all_cached_stream_highlights.py
streamanalyser/fonts/NotoSansCJKjp-Bold.ttf
streamanalyser/modules/__init__.py
streamanalyser/modules/chatanalyser.py
streamanalyser/modules/cli.py
streamanalyser/modules/datacollector.py
streamanalyser/modules/datarefiner.py
streamanalyser/modules/exceptions.py
streamanalyser/modules/filehandler.py
streamanalyser/modules/keyphrase_finder.py
streamanalyser/modules/loggersetup.py
streamanalyser/modules/structures.py
streamanalyser/modules/utils.py
streamanalyser/tests/__init__.py
streamanalyser/tests/test_chatanalyser.py
streamanalyser/tests/test_datacollector.py
streamanalyser/tests/test_datarefiner.py
streamanalyser/tests/test_loggersetup.py
streamanalyser/tests/test_streamanalyser.py
stream_analyser-0.3.8.dist-info/LICENSE
stream_analyser-0.3.8.dist-info/METADATA
stream_analyser-0.3.8.dist-info/WHEEL
stream_analyser-0.3.8.dist-info/entry_points.txt
stream_analyser-0.3.8.dist-info/top_level.txt
stream_analyser-0.3.8.dist-info/RECORD
