Metadata-Version: 2.1
Name: stream-analyser
Version: 0.3.8
Summary: A tool that analyses live streams
Home-page: https://github.com/emso-c/stream-analyser
Author: emso-c
Author-email: emsoc192@gmail.com
Keywords: youtube,live,stream,chat,highlight,analysis
Classifier: Development Status :: 4 - Beta
Classifier: License :: OSI Approved :: GNU General Public License v3 (GPLv3)
Classifier: Operating System :: Microsoft :: Windows :: Windows 10
Classifier: Operating System :: POSIX :: Linux
Classifier: Environment :: Console
Classifier: Natural Language :: English
Classifier: Intended Audience :: Developers
Classifier: Intended Audience :: Science/Research
Classifier: Programming Language :: Python
Classifier: Topic :: Scientific/Engineering
Classifier: Topic :: Scientific/Engineering :: Information Analysis
Requires-Python: >=3.7
License-File: LICENSE
Requires-Dist: appdirs (>=1.4.4)
Requires-Dist: black (>=21.7b0)
Requires-Dist: build (>=0.6.0.post1)
Requires-Dist: certifi (>=2021.5.30)
Requires-Dist: charset-normalizer (>=2.0.4)
Requires-Dist: chat-downloader (>=0.1.8)
Requires-Dist: click (>=8.0.1)
Requires-Dist: colorama (>=0.4.4)
Requires-Dist: colorlog (>=5.0.1)
Requires-Dist: coverage (>=5.5)
Requires-Dist: cycler (>=0.10.0)
Requires-Dist: docstring-parser (>=0.10)
Requires-Dist: idna (>=3.2)
Requires-Dist: isodate (>=0.6.0)
Requires-Dist: joblib (>=1.1.0)
Requires-Dist: kiwisolver (>=1.3.1)
Requires-Dist: matplotlib (>=3.4.3)
Requires-Dist: mypy-extensions (>=0.4.3)
Requires-Dist: nltk (>=3.6.7)
Requires-Dist: numpy (>=1.23.3)
Requires-Dist: packaging (>=21.0)
Requires-Dist: pathspec (>=0.9.0)
Requires-Dist: pep517 (>=0.11.0)
Requires-Dist: Pillow (>=9.0.1)
Requires-Dist: pyparsing (>=2.4.7)
Requires-Dist: python-dateutil (>=2.8.2)
Requires-Dist: PyYAML (>=5.4.1)
Requires-Dist: regex (>=2021.8.3)
Requires-Dist: requests (>=2.26.0)
Requires-Dist: six (>=1.16.0)
Requires-Dist: tomli (>=1.2.1)
Requires-Dist: tqdm (>=4.62.3)
Requires-Dist: urllib3 (>=1.26.6)
Requires-Dist: websocket-client (>=1.2.1)
Requires-Dist: wordcloud (>=1.8.1)
